bulkflow/__init__.py
bulkflow/main.py
bulkflow/database/__init__.py
bulkflow/database/db_utils.py
bulkflow/database/postgres_loader.py
bulkflow/models/__init__.py
bulkflow/models/processing_state.py
bulkflow/processors/__init__.py
bulkflow/processors/csv_processor.py
bulkflow/processors/import_manager.py
bulkflow/utils/__init__.py
bulkflow/utils/logging_config.py
bulkflow-0.1.4.dist-info/LICENSE
bulkflow-0.1.4.dist-info/METADATA
bulkflow-0.1.4.dist-info/WHEEL
bulkflow-0.1.4.dist-info/entry_points.txt
bulkflow-0.1.4.dist-info/top_level.txt
bulkflow-0.1.4.dist-info/RECORD
