Metadata-Version: 2.1
Name: bulkflow
Version: 0.1.4
Summary: A high-performance CSV to PostgreSQL data loader with chunked processing and error handling
Home-page: https://github.com/clwillingham/bulkflow
Author: Chris
Author-email: clwillingham@gmail.com
Project-URL: Bug Tracker, https://github.com/clwillingham/bulkflow/issues
Project-URL: Documentation, https://github.com/clwillingham/bulkflow
Project-URL: Source Code, https://github.com/clwillingham/bulkflow
Keywords: postgresql csv data-loading etl database bulk-import data-processing
Classifier: Development Status :: 4 - Beta
Classifier: Intended Audience :: Developers
Classifier: Topic :: Database
Classifier: Topic :: Software Development :: Libraries :: Python Modules
Classifier: Programming Language :: Python :: 3
Classifier: Programming Language :: Python :: 3.7
Classifier: Programming Language :: Python :: 3.8
Classifier: Programming Language :: Python :: 3.9
Classifier: Programming Language :: Python :: 3.10
Classifier: Programming Language :: Python :: 3.11
Classifier: Programming Language :: Python :: 3.12
Classifier: License :: OSI Approved :: MIT License
Classifier: Operating System :: OS Independent
Requires-Python: >=3.7
License-File: LICENSE
Requires-Dist: psycopg2-binary >=2.9.0
